mood_recommender-0.1.3.dist-info/licenses/LICENSE.txt
mood_suggester/__init__.py
mood_suggester/activity.py
mood_suggester/book.py
mood_suggester/movie.py
mood_suggester/music.py
mood_recommender-0.1.3.dist-info/METADATA
mood_recommender-0.1.3.dist-info/WHEEL
mood_recommender-0.1.3.dist-info/top_level.txt
mood_recommender-0.1.3.dist-info/RECORD
