Metadata-Version: 2.4
Name: mood_recommender
Version: 0.1.3
Summary: A package to suggest activities based on mood.
Home-page: https://github.com/software-students-spring2025/3-python-package-chugthiskoolaid
Author: Hao Yang, Yukun Dong, Jess Liang, Yifan Zhang
Author-email: hy2640@nyu.edu, yd2578@nyu.edu, jl13594@nyu.edu, yz9016@nyu.edu
Classifier: Programming Language :: Python :: 3
Classifier: License :: OSI Approved :: MIT License
Classifier: Operating System :: OS Independent
Requires-Python: >=3.6
License-File: LICENSE.txt
Dynamic: author
Dynamic: author-email
Dynamic: classifier
Dynamic: description
Dynamic: description-content-type
Dynamic: home-page
Dynamic: license-file
Dynamic: requires-python
Dynamic: summary
